spaceops/__init__.py
spaceops/benchmark.py
spaceops/cli.py
spaceops/client.py
spaceops/diff.py
spaceops/models.py
spaceops/py.typed
spaceops-0.2.1.dist-info/METADATA
spaceops-0.2.1.dist-info/WHEEL
spaceops-0.2.1.dist-info/entry_points.txt
spaceops-0.2.1.dist-info/top_level.txt
spaceops-0.2.1.dist-info/RECORD
