Metadata-Version: 2.4
Name: spaceops
Version: 0.2.1
Summary: CI/CD pipeline for Databricks Genie spaces - multi-workspace promotion at scale
Author: SpaceOps Team
Author-email: SpaceOps Team <spaceops@example.com>
Maintainer-email: SpaceOps Team <spaceops@example.com>
License: MIT
Project-URL: Homepage, https://github.com/charotAmine/databricks-spaceops
Project-URL: Documentation, https://github.com/charotAmine/databricks-spaceops#readme
Project-URL: Repository, https://github.com/charotAmine/databricks-spaceops.git
Project-URL: Issues, https://github.com/charotAmine/databricks-spaceops/issues
Project-URL: Changelog, https://github.com/charotAmine/databricks-spaceops/blob/main/CHANGELOG.md
Keywords: databricks,genie,ai-bi,cicd,mlops,data-engineering,analytics
Classifier: Development Status :: 4 - Beta
Classifier: Environment :: Console
Classifier: Intended Audience :: Developers
Classifier: Intended Audience :: System Administrators
Classifier: License :: OSI Approved :: MIT License
Classifier: Operating System :: OS Independent
Classifier: Programming Language :: Python :: 3
Classifier: Programming Language :: Python :: 3.10
Classifier: Programming Language :: Python :: 3.11
Classifier: Programming Language :: Python :: 3.12
Classifier: Topic :: Software Development :: Build Tools
Classifier: Topic :: System :: Systems Administration
Classifier: Typing :: Typed
Requires-Python: >=3.10
Requires-Dist: click>=8.1.0
Requires-Dist: httpx>=0.27.0
Requires-Dist: pydantic>=2.5.0
Requires-Dist: pyyaml>=6.0.0
Requires-Dist: rich>=13.7.0
Requires-Dist: deepdiff>=7.0.0
Requires-Dist: python-dotenv>=1.0.0
Provides-Extra: dev
Requires-Dist: pytest>=8.0.0; extra == "dev"
Requires-Dist: pytest-asyncio>=0.23.0; extra == "dev"
Requires-Dist: pytest-cov>=4.1.0; extra == "dev"
Requires-Dist: ruff>=0.1.0; extra == "dev"
Requires-Dist: mypy>=1.8.0; extra == "dev"
Requires-Dist: types-PyYAML>=6.0.0; extra == "dev"
Dynamic: author
Dynamic: requires-python
